zope.deprecation-5.0-py3.9-nspkg.pth
zope/deprecation/__init__.py
zope/deprecation/deprecation.py
zope/deprecation/fixture.py
zope/deprecation/tests.py
zope.deprecation-5.0.dist-info/LICENSE.txt
zope.deprecation-5.0.dist-info/METADATA
zope.deprecation-5.0.dist-info/WHEEL
zope.deprecation-5.0.dist-info/namespace_packages.txt
zope.deprecation-5.0.dist-info/top_level.txt
zope.deprecation-5.0.dist-info/RECORD
